{"data":{"sitePage":{"context":{"data":"<p>Ciao vieni a vedermi lol</p>","titolo":"10 Maggio rally dei presi bene","mainImage":{"fields":{"file":{"url":"//images.ctfassets.net/4hdczd41xjc6/10NT2VX5rieII6ea0Q2CCk/d4bbfa814e2c050cc23fb66d20927f51/Untitled.png"}}}}}},"pageContext":{"identifier":"10VNyzeB2UgKs0QmyWUMyM","titolo":"10 Maggio rally dei presi bene","data":"<p>Ciao vieni a vedermi lol</p>","slug":"/blog/10maggiolol","mainImage":{"sys":{"space":{"sys":{"type":"Link","linkType":"Space","id":"4hdczd41xjc6"}},"id":"10NT2VX5rieII6ea0Q2CCk","type":"Asset","createdAt":"2018-11-26T09:13:33.242Z","updatedAt":"2018-11-26T09:13:33.242Z","environment":{"sys":{"id":"master","type":"Link","linkType":"Environment"}},"revision":1,"locale":"en-US"},"fields":{"title":"Untitled","file":{"url":"//images.ctfassets.net/4hdczd41xjc6/10NT2VX5rieII6ea0Q2CCk/d4bbfa814e2c050cc23fb66d20927f51/Untitled.png","details":{"size":170253,"image":{"width":1920,"height":1080}},"fileName":"Untitled.png","contentType":"image/png"}}}}}