{"data":{"sitePage":{"context":{"data":"<p>Ciao vieni a vedermi lol</p>","titolo":"10 Maggio rally dei presi bene","mainImage":{"fields":{"file":{"url":"//images.ctfassets.net/4hdczd41xjc6/10NT2VX5rieII6ea0Q2CCk/d4bbfa814e2c050cc23fb66d20927f51/Untitled.png"}}},"gallery":[{"fields":{"file":{"url":"//images.ctfassets.net/4hdczd41xjc6/LC6nslnUcu8UWqC86yKWI/45bfe2279ea2d7fdf923df3f3d88ed95/armchair.png"}}},{"fields":{"file":{"url":"//images.ctfassets.net/4hdczd41xjc6/5G96NMARnayWsQs8OSAE2E/deb6e0f1080d89ce60d2e72b53d6d968/viz.png"}}},{"fields":{"file":{"url":"//images.ctfassets.net/4hdczd41xjc6/5qstpKU8ucqismok8w4eoK/2bfc09c965053c4e4ca04ba128b8b5a3/404.png"}}}]}}},"pageContext":{"identifier":"10VNyzeB2UgKs0QmyWUMyM","titolo":"10 Maggio rally dei presi bene","data":"<p>Ciao vieni a vedermi lol</p>","slug":"/blog/10maggiolol","mainImage":{"sys":{"space":{"sys":{"type":"Link","linkType":"Space","id":"4hdczd41xjc6"}},"id":"10NT2VX5rieII6ea0Q2CCk","type":"Asset","createdAt":"2018-11-26T09:13:33.242Z","updatedAt":"2018-11-26T09:13:33.242Z","environment":{"sys":{"id":"master","type":"Link","linkType":"Environment"}},"revision":1,"locale":"en-US"},"fields":{"title":"Untitled","file":{"url":"//images.ctfassets.net/4hdczd41xjc6/10NT2VX5rieII6ea0Q2CCk/d4bbfa814e2c050cc23fb66d20927f51/Untitled.png","details":{"size":170253,"image":{"width":1920,"height":1080}},"fileName":"Untitled.png","contentType":"image/png"}}},"gallery":[{"sys":{"space":{"sys":{"type":"Link","linkType":"Space","id":"4hdczd41xjc6"}},"id":"LC6nslnUcu8UWqC86yKWI","type":"Asset","createdAt":"2018-11-26T09:15:03.825Z","updatedAt":"2018-11-26T09:15:03.825Z","environment":{"sys":{"id":"master","type":"Link","linkType":"Environment"}},"revision":1,"locale":"en-US"},"fields":{"title":"armchair","file":{"url":"//images.ctfassets.net/4hdczd41xjc6/LC6nslnUcu8UWqC86yKWI/45bfe2279ea2d7fdf923df3f3d88ed95/armchair.png","details":{"size":43444,"image":{"width":900,"height":540}},"fileName":"armchair.png","contentType":"image/jpeg"}}},{"sys":{"space":{"sys":{"type":"Link","linkType":"Space","id":"4hdczd41xjc6"}},"id":"5G96NMARnayWsQs8OSAE2E","type":"Asset","createdAt":"2018-11-26T09:16:01.673Z","updatedAt":"2018-11-26T09:16:01.673Z","environment":{"sys":{"id":"master","type":"Link","linkType":"Environment"}},"revision":1,"locale":"en-US"},"fields":{"title":"viz","file":{"url":"//images.ctfassets.net/4hdczd41xjc6/5G96NMARnayWsQs8OSAE2E/deb6e0f1080d89ce60d2e72b53d6d968/viz.png","details":{"size":812912,"image":{"width":1509,"height":927}},"fileName":"viz.png","contentType":"image/png"}}},{"sys":{"space":{"sys":{"type":"Link","linkType":"Space","id":"4hdczd41xjc6"}},"id":"5qstpKU8ucqismok8w4eoK","type":"Asset","createdAt":"2018-11-26T09:16:17.838Z","updatedAt":"2018-11-26T09:16:17.838Z","environment":{"sys":{"id":"master","type":"Link","linkType":"Environment"}},"revision":1,"locale":"en-US"},"fields":{"title":"404","file":{"url":"//images.ctfassets.net/4hdczd41xjc6/5qstpKU8ucqismok8w4eoK/2bfc09c965053c4e4ca04ba128b8b5a3/404.png","details":{"size":23368,"image":{"width":1895,"height":280}},"fileName":"404.png","contentType":"image/png"}}}]}}